JavascriptMoshi/README.md
JavascriptMoshi/__init__.py
JavascriptMoshi/__main__.py
JavascriptMoshi/file.epub
JavascriptMoshi/index.html
JavascriptMoshi/css/__init__.py
JavascriptMoshi/css/annotations.css
JavascriptMoshi/css/main.css
JavascriptMoshi/css/normalize.css
JavascriptMoshi/css/popup.css
JavascriptMoshi/font/__init__.py
JavascriptMoshi/font/fontello.eot
JavascriptMoshi/font/fontello.svg
JavascriptMoshi/font/fontello.ttf
JavascriptMoshi/font/fontello.woff
JavascriptMoshi/img/__init__.py
JavascriptMoshi/img/annotator-glyph-sprite.png
JavascriptMoshi/img/annotator-icon-sprite.png
JavascriptMoshi/img/apple-touch-icon.png
JavascriptMoshi/img/cancelfullscreen.png
JavascriptMoshi/img/close.png
JavascriptMoshi/img/fullscreen.png
JavascriptMoshi/img/loader.gif
JavascriptMoshi/img/menu-icon.png
JavascriptMoshi/img/save.png
JavascriptMoshi/img/saved.png
JavascriptMoshi/img/settings-s.png
JavascriptMoshi/img/settings.png
JavascriptMoshi/img/star.png
JavascriptMoshi/js/__init__.py
JavascriptMoshi/js/epub.js
JavascriptMoshi/js/epub.min.js
JavascriptMoshi/js/epub.min.map
JavascriptMoshi/js/hooks.min.js
JavascriptMoshi/js/hooks.min.map
JavascriptMoshi/js/reader.js
JavascriptMoshi/js/reader.js.map
JavascriptMoshi/js/reader.min.js
JavascriptMoshi/js/reader.min.map
JavascriptMoshi/js/hooks/__init__.py
JavascriptMoshi/js/hooks/extensions/__init__.py
JavascriptMoshi/js/hooks/extensions/highlight.js
JavascriptMoshi/js/libs/__init__.py
JavascriptMoshi/js/libs/jquery.min.js
JavascriptMoshi/js/libs/localforage.min.js
JavascriptMoshi/js/libs/screenfull.js
JavascriptMoshi/js/libs/screenfull.min.js
JavascriptMoshi/js/libs/zip.min.js
JavascriptMoshi/js/plugins/__init__.py
JavascriptMoshi/js/plugins/hypothesis.js
JavascriptMoshi/js/plugins/search.js
javascript_moshi-2024.3.2.0.dist-info/METADATA
javascript_moshi-2024.3.2.0.dist-info/WHEEL
javascript_moshi-2024.3.2.0.dist-info/entry_points.txt
javascript_moshi-2024.3.2.0.dist-info/top_level.txt
javascript_moshi-2024.3.2.0.dist-info/RECORD
